[
  {
    "RANK": 1,
    "MAIN_PUNCT_APT_NAME": "Stockholm Bromma",
    "MAIN_PUNCT_APT_ARR_PUNCT": 0.9429,
    "MAIN_PUNCT_APT_NAME_BOTTOM": "Tel Aviv",
    "MAIN_PUNCT_APT_ARR_PUNCT_BOTTOM": 0.291,
    "DY_RANK_DIF_PREV_WEEK": 27,
    "DY_APT_NAME": "Stockholm Bromma",
    "DY_TO_DATE": "2024-10-28",
    "DY_APT_ARR_PUNCT": 0.9429,
    "DY_PUNCT_DIF_PREV_WEEK_PERC": 0.1343,
    "DY_PUNCT_DIF_PREV_YEAR_PERC": -0.0286,
    "WK_RANK_DIF_PREV_WEEK": 2,
    "WK_APT_NAME": "Bergen",
    "WK_FROM_DATE": "2024-10-22",
    "WK_TO_DATE": "2024-10-28",
    "WK_APT_ARR_PUNCT": 0.8814,
    "WK_PUNCT_DIF_PREV_WEEK_PERC": 0.0012,
    "WK_PUNCT_DIF_PREV_YEAR_PERC": -0.0195,
    "Y2D_RANK_DIF_PREV_YEAR": 1,
    "Y2D_APT_NAME": "Bergen",
    "Y2D_TO_DATE": "2024-10-28",
    "Y2D_APT_ARR_PUNCT": 0.8447,
    "Y2D_PUNCT_DIF_PREV_YEAR_PERC": 0.014,
    "Y2D_PUNCT_DIF_2019_PERC": -0.0068,
    "DY_RANK_DIF_PREV_WEEK_BOTTOM": -1,
    "DY_APT_NAME_BOTTOM": "Tel Aviv",
    "DY_TO_DATE_BOTTOM": "2024-10-28",
    "DY_APT_ARR_PUNCT_BOTTOM": 0.291,
    "DY_PUNCT_DIF_PREV_WEEK_PERC_BOTTOM": -0.0694,
    "DY_PUNCT_DIF_PREV_YEAR_PERC_BOTTOM": -0.2583,
    "WK_RANK_DIF_PREV_WEEK_BOTTOM": 0,
    "WK_APT_NAME_BOTTOM": "Tel Aviv",
    "WK_FROM_DATE_BOTTOM": "2024-10-22",
    "WK_TO_DATE_BOTTOM": "2024-10-28",
    "WK_APT_ARR_PUNCT_BOTTOM": 0.4261,
    "WK_PUNCT_DIF_PREV_WEEK_PERC_BOTTOM": 0.0051,
    "WK_PUNCT_DIF_PREV_YEAR_PERC_BOTTOM": -0.1222,
    "Y2D_RANK_DIF_PREV_YEAR_BOTTOM": -2,
    "Y2D_APT_NAME_BOTTOM": "Antalya",
    "Y2D_TO_DATE_BOTTOM": "2024-10-28",
    "Y2D_APT_ARR_PUNCT_BOTTOM": 0.5429,
    "Y2D_PUNCT_DIF_PREV_YEAR_PERC_BOTTOM": -0.0139,
    "Y2D_PUNCT_DIF_2019_PERC_BOTTOM": -0.1706
  },
  {
    "RANK": 2,
    "MAIN_PUNCT_APT_NAME": "Stavanger",
    "MAIN_PUNCT_APT_ARR_PUNCT": 0.9286,
    "MAIN_PUNCT_APT_NAME_BOTTOM": "Barcelona",
    "MAIN_PUNCT_APT_ARR_PUNCT_BOTTOM": 0.4472,
    "DY_RANK_DIF_PREV_WEEK": 37,
    "DY_APT_NAME": "Stavanger",
    "DY_TO_DATE": "2024-10-28",
    "DY_APT_ARR_PUNCT": 0.9286,
    "DY_PUNCT_DIF_PREV_WEEK_PERC": 0.1313,
    "DY_PUNCT_DIF_PREV_YEAR_PERC": 0.2909,
    "WK_RANK_DIF_PREV_WEEK": 2,
    "WK_APT_NAME": "Stavanger",
    "WK_FROM_DATE": "2024-10-22",
    "WK_TO_DATE": "2024-10-28",
    "WK_APT_ARR_PUNCT": 0.8787,
    "WK_PUNCT_DIF_PREV_WEEK_PERC": 0.0174,
    "WK_PUNCT_DIF_PREV_YEAR_PERC": 0.0352,
    "Y2D_RANK_DIF_PREV_YEAR": -1,
    "Y2D_APT_NAME": "Stockholm Bromma",
    "Y2D_TO_DATE": "2024-10-28",
    "Y2D_APT_ARR_PUNCT": 0.8431,
    "Y2D_PUNCT_DIF_PREV_YEAR_PERC": 0.0069,
    "Y2D_PUNCT_DIF_2019_PERC": -0.0711,
    "DY_RANK_DIF_PREV_WEEK_BOTTOM": -46,
    "DY_APT_NAME_BOTTOM": "Barcelona",
    "DY_TO_DATE_BOTTOM": "2024-10-28",
    "DY_APT_ARR_PUNCT_BOTTOM": 0.4472,
    "DY_PUNCT_DIF_PREV_WEEK_PERC_BOTTOM": -0.3168,
    "DY_PUNCT_DIF_PREV_YEAR_PERC_BOTTOM": -0.2217,
    "WK_RANK_DIF_PREV_WEEK_BOTTOM": -4,
    "WK_APT_NAME_BOTTOM": "Tbilisi",
    "WK_FROM_DATE_BOTTOM": "2024-10-22",
    "WK_TO_DATE_BOTTOM": "2024-10-28",
    "WK_APT_ARR_PUNCT_BOTTOM": 0.5961,
    "WK_PUNCT_DIF_PREV_WEEK_PERC_BOTTOM": -0.0018,
    "WK_PUNCT_DIF_PREV_YEAR_PERC_BOTTOM": -0.1548,
    "Y2D_RANK_DIF_PREV_YEAR_BOTTOM": -7,
    "Y2D_APT_NAME_BOTTOM": "Tel Aviv",
    "Y2D_TO_DATE_BOTTOM": "2024-10-28",
    "Y2D_APT_ARR_PUNCT_BOTTOM": 0.5717,
    "Y2D_PUNCT_DIF_PREV_YEAR_PERC_BOTTOM": -0.0339,
    "Y2D_PUNCT_DIF_2019_PERC_BOTTOM": -0.1072
  },
  {
    "RANK": 3,
    "MAIN_PUNCT_APT_NAME": "Podgorica",
    "MAIN_PUNCT_APT_ARR_PUNCT": 0.9231,
    "MAIN_PUNCT_APT_NAME_BOTTOM": "Yerevan",
    "MAIN_PUNCT_APT_ARR_PUNCT_BOTTOM": 0.4667,
    "DY_RANK_DIF_PREV_WEEK": 43,
    "DY_APT_NAME": "Podgorica",
    "DY_TO_DATE": "2024-10-28",
    "DY_APT_ARR_PUNCT": 0.9231,
    "DY_PUNCT_DIF_PREV_WEEK_PERC": 0.1336,
    "DY_PUNCT_DIF_PREV_YEAR_PERC": -0.0055,
    "WK_RANK_DIF_PREV_WEEK": -1,
    "WK_APT_NAME": "Stockholm Bromma",
    "WK_FROM_DATE": "2024-10-22",
    "WK_TO_DATE": "2024-10-28",
    "WK_APT_ARR_PUNCT": 0.8664,
    "WK_PUNCT_DIF_PREV_WEEK_PERC": -0.0183,
    "WK_PUNCT_DIF_PREV_YEAR_PERC": -0.0528,
    "Y2D_RANK_DIF_PREV_YEAR": 1,
    "Y2D_APT_NAME": "Trondheim",
    "Y2D_TO_DATE": "2024-10-28",
    "Y2D_APT_ARR_PUNCT": 0.8368,
    "Y2D_PUNCT_DIF_PREV_YEAR_PERC": 0.0191,
    "Y2D_PUNCT_DIF_2019_PERC": -0.0017,
    "DY_RANK_DIF_PREV_WEEK_BOTTOM": 0,
    "DY_APT_NAME_BOTTOM": "Yerevan",
    "DY_TO_DATE_BOTTOM": "2024-10-28",
    "DY_APT_ARR_PUNCT_BOTTOM": 0.4667,
    "DY_PUNCT_DIF_PREV_WEEK_PERC_BOTTOM": -0.0333,
    "DY_PUNCT_DIF_PREV_YEAR_PERC_BOTTOM": -0.4281,
    "WK_RANK_DIF_PREV_WEEK_BOTTOM": 1,
    "WK_APT_NAME_BOTTOM": "London Gatwick",
    "WK_FROM_DATE_BOTTOM": "2024-10-22",
    "WK_TO_DATE_BOTTOM": "2024-10-28",
    "WK_APT_ARR_PUNCT_BOTTOM": 0.6051,
    "WK_PUNCT_DIF_PREV_WEEK_PERC_BOTTOM": 0.124,
    "WK_PUNCT_DIF_PREV_YEAR_PERC_BOTTOM": 0.0223,
    "Y2D_RANK_DIF_PREV_YEAR_BOTTOM": 1,
    "Y2D_APT_NAME_BOTTOM": "Paris Le Bourget",
    "Y2D_TO_DATE_BOTTOM": "2024-10-28",
    "Y2D_APT_ARR_PUNCT_BOTTOM": 0.5803,
    "Y2D_PUNCT_DIF_PREV_YEAR_PERC_BOTTOM": 0.0518,
    "Y2D_PUNCT_DIF_2019_PERC_BOTTOM": 0.0188
  },
  {
    "RANK": 4,
    "MAIN_PUNCT_APT_NAME": "Faro",
    "MAIN_PUNCT_APT_ARR_PUNCT": 0.9189,
    "MAIN_PUNCT_APT_NAME_BOTTOM": "Nantes",
    "MAIN_PUNCT_APT_ARR_PUNCT_BOTTOM": 0.4872,
    "DY_RANK_DIF_PREV_WEEK": 98,
    "DY_APT_NAME": "Faro",
    "DY_TO_DATE": "2024-10-28",
    "DY_APT_ARR_PUNCT": 0.9189,
    "DY_PUNCT_DIF_PREV_WEEK_PERC": 0.3087,
    "DY_PUNCT_DIF_PREV_YEAR_PERC": 0.3053,
    "WK_RANK_DIF_PREV_WEEK": 12,
    "WK_APT_NAME": "Ankara",
    "WK_FROM_DATE": "2024-10-22",
    "WK_TO_DATE": "2024-10-28",
    "WK_APT_ARR_PUNCT": 0.855,
    "WK_PUNCT_DIF_PREV_WEEK_PERC": 0.0539,
    "WK_PUNCT_DIF_PREV_YEAR_PERC": 0.2975,
    "Y2D_RANK_DIF_PREV_YEAR": 1,
    "Y2D_APT_NAME": "Stavanger",
    "Y2D_TO_DATE": "2024-10-28",
    "Y2D_APT_ARR_PUNCT": 0.8285,
    "Y2D_PUNCT_DIF_PREV_YEAR_PERC": 0.0192,
    "Y2D_PUNCT_DIF_2019_PERC": -0.0152,
    "DY_RANK_DIF_PREV_WEEK_BOTTOM": -72,
    "DY_APT_NAME_BOTTOM": "Nantes",
    "DY_TO_DATE_BOTTOM": "2024-10-28",
    "DY_APT_ARR_PUNCT_BOTTOM": 0.4872,
    "DY_PUNCT_DIF_PREV_WEEK_PERC_BOTTOM": -0.3128,
    "DY_PUNCT_DIF_PREV_YEAR_PERC_BOTTOM": -0.1503,
    "WK_RANK_DIF_PREV_WEEK_BOTTOM": -33,
    "WK_APT_NAME_BOTTOM": "Barcelona",
    "WK_FROM_DATE_BOTTOM": "2024-10-22",
    "WK_TO_DATE_BOTTOM": "2024-10-28",
    "WK_APT_ARR_PUNCT_BOTTOM": 0.6104,
    "WK_PUNCT_DIF_PREV_WEEK_PERC_BOTTOM": -0.0952,
    "WK_PUNCT_DIF_PREV_YEAR_PERC_BOTTOM": -0.1102,
    "Y2D_RANK_DIF_PREV_YEAR_BOTTOM": 3,
    "Y2D_APT_NAME_BOTTOM": "Chisinau",
    "Y2D_TO_DATE_BOTTOM": "2024-10-28",
    "Y2D_APT_ARR_PUNCT_BOTTOM": 0.5884,
    "Y2D_PUNCT_DIF_PREV_YEAR_PERC_BOTTOM": 0.0662,
    "Y2D_PUNCT_DIF_2019_PERC_BOTTOM": -0.0876
  },
  {
    "RANK": 5,
    "DY_RANK_DIF_PREV_WEEK": 51,
    "DY_APT_NAME": "Tenerife Sur",
    "DY_TO_DATE": "2024-10-28",
    "DY_APT_ARR_PUNCT": 0.916,
    "DY_PUNCT_DIF_PREV_WEEK_PERC": 0.1428,
    "DY_PUNCT_DIF_PREV_YEAR_PERC": 0.5196,
    "WK_RANK_DIF_PREV_WEEK": 27,
    "WK_APT_NAME": "Milan Linate",
    "WK_FROM_DATE": "2024-10-22",
    "WK_TO_DATE": "2024-10-28",
    "WK_APT_ARR_PUNCT": 0.8475,
    "WK_PUNCT_DIF_PREV_WEEK_PERC": 0.0923,
    "WK_PUNCT_DIF_PREV_YEAR_PERC": 0.0977,
    "Y2D_RANK_DIF_PREV_YEAR": 1,
    "Y2D_APT_NAME": "Bilbao",
    "Y2D_TO_DATE": "2024-10-28",
    "Y2D_APT_ARR_PUNCT": 0.8256,
    "Y2D_PUNCT_DIF_PREV_YEAR_PERC": 0.0181,
    "Y2D_PUNCT_DIF_2019_PERC": -0.0036,
    "DY_RANK_DIF_PREV_WEEK_BOTTOM": -72,
    "DY_APT_NAME_BOTTOM": "Frankfurt",
    "DY_TO_DATE_BOTTOM": "2024-10-28",
    "DY_APT_ARR_PUNCT_BOTTOM": 0.4972,
    "DY_PUNCT_DIF_PREV_WEEK_PERC_BOTTOM": -0.3028,
    "DY_PUNCT_DIF_PREV_YEAR_PERC_BOTTOM": -0.3307,
    "WK_RANK_DIF_PREV_WEEK_BOTTOM": -28,
    "WK_APT_NAME_BOTTOM": "Yerevan",
    "WK_FROM_DATE_BOTTOM": "2024-10-22",
    "WK_TO_DATE_BOTTOM": "2024-10-28",
    "WK_APT_ARR_PUNCT_BOTTOM": 0.6118,
    "WK_PUNCT_DIF_PREV_WEEK_PERC_BOTTOM": -0.0857,
    "WK_PUNCT_DIF_PREV_YEAR_PERC_BOTTOM": -0.1882,
    "Y2D_RANK_DIF_PREV_YEAR_BOTTOM": 0,
    "Y2D_APT_NAME_BOTTOM": "Belgrade",
    "Y2D_TO_DATE_BOTTOM": "2024-10-28",
    "Y2D_APT_ARR_PUNCT_BOTTOM": 0.5964,
    "Y2D_PUNCT_DIF_PREV_YEAR_PERC_BOTTOM": 0.0193,
    "Y2D_PUNCT_DIF_2019_PERC_BOTTOM": -0.1043
  },
  {
    "RANK": 6,
    "DY_RANK_DIF_PREV_WEEK": 43,
    "DY_APT_NAME": "Gothenburg",
    "DY_TO_DATE": "2024-10-28",
    "DY_APT_ARR_PUNCT": 0.9016,
    "DY_PUNCT_DIF_PREV_WEEK_PERC": 0.1179,
    "DY_PUNCT_DIF_PREV_YEAR_PERC": 0.1113,
    "WK_RANK_DIF_PREV_WEEK": 1,
    "WK_APT_NAME": "Oslo",
    "WK_FROM_DATE": "2024-10-22",
    "WK_TO_DATE": "2024-10-28",
    "WK_APT_ARR_PUNCT": 0.8442,
    "WK_PUNCT_DIF_PREV_WEEK_PERC": 0.0146,
    "WK_PUNCT_DIF_PREV_YEAR_PERC": 0.0257,
    "Y2D_RANK_DIF_PREV_YEAR": 4,
    "Y2D_APT_NAME": "London City",
    "Y2D_TO_DATE": "2024-10-28",
    "Y2D_APT_ARR_PUNCT": 0.8019,
    "Y2D_PUNCT_DIF_PREV_YEAR_PERC": 0.014,
    "Y2D_PUNCT_DIF_2019_PERC": -0.0013,
    "DY_RANK_DIF_PREV_WEEK_BOTTOM": -5,
    "DY_APT_NAME_BOTTOM": "Geneva",
    "DY_TO_DATE_BOTTOM": "2024-10-28",
    "DY_APT_ARR_PUNCT_BOTTOM": 0.5099,
    "DY_PUNCT_DIF_PREV_WEEK_PERC_BOTTOM": -0.1102,
    "DY_PUNCT_DIF_PREV_YEAR_PERC_BOTTOM": -0.2679,
    "WK_RANK_DIF_PREV_WEEK_BOTTOM": -72,
    "WK_APT_NAME_BOTTOM": "Nantes",
    "WK_FROM_DATE_BOTTOM": "2024-10-22",
    "WK_TO_DATE_BOTTOM": "2024-10-28",
    "WK_APT_ARR_PUNCT_BOTTOM": 0.6154,
    "WK_PUNCT_DIF_PREV_WEEK_PERC_BOTTOM": -0.1379,
    "WK_PUNCT_DIF_PREV_YEAR_PERC_BOTTOM": -0.043,
    "Y2D_RANK_DIF_PREV_YEAR_BOTTOM": 2,
    "Y2D_APT_NAME_BOTTOM": "London Gatwick",
    "Y2D_TO_DATE_BOTTOM": "2024-10-28",
    "Y2D_APT_ARR_PUNCT_BOTTOM": 0.6139,
    "Y2D_PUNCT_DIF_PREV_YEAR_PERC_BOTTOM": 0.051,
    "Y2D_PUNCT_DIF_2019_PERC_BOTTOM": -0.0515
  },
  {
    "RANK": 7,
    "DY_RANK_DIF_PREV_WEEK": 23,
    "DY_APT_NAME": "Palermo",
    "DY_TO_DATE": "2024-10-28",
    "DY_APT_ARR_PUNCT": 0.8955,
    "DY_PUNCT_DIF_PREV_WEEK_PERC": 0.0894,
    "DY_PUNCT_DIF_PREV_YEAR_PERC": 0.2338,
    "WK_RANK_DIF_PREV_WEEK": 3,
    "WK_APT_NAME": "Stockholm Arlanda",
    "WK_FROM_DATE": "2024-10-22",
    "WK_TO_DATE": "2024-10-28",
    "WK_APT_ARR_PUNCT": 0.8365,
    "WK_PUNCT_DIF_PREV_WEEK_PERC": 0.019,
    "WK_PUNCT_DIF_PREV_YEAR_PERC": 0.0387,
    "Y2D_RANK_DIF_PREV_YEAR": 2,
    "Y2D_APT_NAME": "Oslo",
    "Y2D_TO_DATE": "2024-10-28",
    "Y2D_APT_ARR_PUNCT": 0.7999,
    "Y2D_PUNCT_DIF_PREV_YEAR_PERC": 0.0097,
    "Y2D_PUNCT_DIF_2019_PERC": -0.0102,
    "DY_RANK_DIF_PREV_WEEK_BOTTOM": -92,
    "DY_APT_NAME_BOTTOM": "Bilbao",
    "DY_TO_DATE_BOTTOM": "2024-10-28",
    "DY_APT_ARR_PUNCT_BOTTOM": 0.5493,
    "DY_PUNCT_DIF_PREV_WEEK_PERC_BOTTOM": -0.2882,
    "DY_PUNCT_DIF_PREV_YEAR_PERC_BOTTOM": -0.2632,
    "WK_RANK_DIF_PREV_WEEK_BOTTOM": -2,
    "WK_APT_NAME_BOTTOM": "Paris Le Bourget",
    "WK_FROM_DATE_BOTTOM": "2024-10-22",
    "WK_TO_DATE_BOTTOM": "2024-10-28",
    "WK_APT_ARR_PUNCT_BOTTOM": 0.6214,
    "WK_PUNCT_DIF_PREV_WEEK_PERC_BOTTOM": -0.0182,
    "WK_PUNCT_DIF_PREV_YEAR_PERC_BOTTOM": 0.0984,
    "Y2D_RANK_DIF_PREV_YEAR_BOTTOM": -3,
    "Y2D_APT_NAME_BOTTOM": "Lisbon",
    "Y2D_TO_DATE_BOTTOM": "2024-10-28",
    "Y2D_APT_ARR_PUNCT_BOTTOM": 0.6145,
    "Y2D_PUNCT_DIF_PREV_YEAR_PERC_BOTTOM": 0.0075,
    "Y2D_PUNCT_DIF_2019_PERC_BOTTOM": -0.0374
  },
  {
    "RANK": 8,
    "DY_RANK_DIF_PREV_WEEK": 47,
    "DY_APT_NAME": "Ankara",
    "DY_TO_DATE": "2024-10-28",
    "DY_APT_ARR_PUNCT": 0.8857,
    "DY_PUNCT_DIF_PREV_WEEK_PERC": 0.1121,
    "DY_PUNCT_DIF_PREV_YEAR_PERC": 0.1007,
    "WK_RANK_DIF_PREV_WEEK": 33,
    "WK_APT_NAME": "Tenerife Sur",
    "WK_FROM_DATE": "2024-10-22",
    "WK_TO_DATE": "2024-10-28",
    "WK_APT_ARR_PUNCT": 0.8363,
    "WK_PUNCT_DIF_PREV_WEEK_PERC": 0.0924,
    "WK_PUNCT_DIF_PREV_YEAR_PERC": 0.2872,
    "Y2D_RANK_DIF_PREV_YEAR": 15,
    "Y2D_APT_NAME": "Stockholm Arlanda",
    "Y2D_TO_DATE": "2024-10-28",
    "Y2D_APT_ARR_PUNCT": 0.7957,
    "Y2D_PUNCT_DIF_PREV_YEAR_PERC": 0.0437,
    "Y2D_PUNCT_DIF_2019_PERC": 0.0118,
    "DY_RANK_DIF_PREV_WEEK_BOTTOM": -8,
    "DY_APT_NAME_BOTTOM": "Paris Le Bourget",
    "DY_TO_DATE_BOTTOM": "2024-10-28",
    "DY_APT_ARR_PUNCT_BOTTOM": 0.5625,
    "DY_PUNCT_DIF_PREV_WEEK_PERC_BOTTOM": -0.0775,
    "DY_PUNCT_DIF_PREV_YEAR_PERC_BOTTOM": 0.0387,
    "WK_RANK_DIF_PREV_WEEK_BOTTOM": 4,
    "WK_APT_NAME_BOTTOM": "Warsaw Chopin",
    "WK_FROM_DATE_BOTTOM": "2024-10-22",
    "WK_TO_DATE_BOTTOM": "2024-10-28",
    "WK_APT_ARR_PUNCT_BOTTOM": 0.6247,
    "WK_PUNCT_DIF_PREV_WEEK_PERC_BOTTOM": 0.0549,
    "WK_PUNCT_DIF_PREV_YEAR_PERC_BOTTOM": -0.2027,
    "Y2D_RANK_DIF_PREV_YEAR_BOTTOM": -16,
    "Y2D_APT_NAME_BOTTOM": "Heraklion",
    "Y2D_TO_DATE_BOTTOM": "2024-10-28",
    "Y2D_APT_ARR_PUNCT_BOTTOM": 0.629,
    "Y2D_PUNCT_DIF_PREV_YEAR_PERC_BOTTOM": -0.0336,
    "Y2D_PUNCT_DIF_2019_PERC_BOTTOM": -0.1048
  },
  {
    "RANK": 9,
    "DY_RANK_DIF_PREV_WEEK": 0,
    "DY_APT_NAME": "Copenhagen",
    "DY_TO_DATE": "2024-10-28",
    "DY_APT_ARR_PUNCT": 0.8827,
    "DY_PUNCT_DIF_PREV_WEEK_PERC": 0.0373,
    "DY_PUNCT_DIF_PREV_YEAR_PERC": 0.0723,
    "WK_RANK_DIF_PREV_WEEK": 17,
    "WK_APT_NAME": "Leipzig/Halle",
    "WK_FROM_DATE": "2024-10-22",
    "WK_TO_DATE": "2024-10-28",
    "WK_APT_ARR_PUNCT": 0.8351,
    "WK_PUNCT_DIF_PREV_WEEK_PERC": 0.0622,
    "WK_PUNCT_DIF_PREV_YEAR_PERC": 0.0509,
    "Y2D_RANK_DIF_PREV_YEAR": 2,
    "Y2D_APT_NAME": "Seville",
    "Y2D_TO_DATE": "2024-10-28",
    "Y2D_APT_ARR_PUNCT": 0.7856,
    "Y2D_PUNCT_DIF_PREV_YEAR_PERC": 0.002,
    "Y2D_PUNCT_DIF_2019_PERC": -0.0738,
    "DY_RANK_DIF_PREV_WEEK_BOTTOM": -60,
    "DY_APT_NAME_BOTTOM": "Thessaloniki",
    "DY_TO_DATE_BOTTOM": "2024-10-28",
    "DY_APT_ARR_PUNCT_BOTTOM": 0.5789,
    "DY_PUNCT_DIF_PREV_WEEK_PERC_BOTTOM": -0.2162,
    "DY_PUNCT_DIF_PREV_YEAR_PERC_BOTTOM": -0.2598,
    "WK_RANK_DIF_PREV_WEEK_BOTTOM": -47,
    "WK_APT_NAME_BOTTOM": "Larnaca",
    "WK_FROM_DATE_BOTTOM": "2024-10-22",
    "WK_TO_DATE_BOTTOM": "2024-10-28",
    "WK_APT_ARR_PUNCT_BOTTOM": 0.6333,
    "WK_PUNCT_DIF_PREV_WEEK_PERC_BOTTOM": -0.0994,
    "WK_PUNCT_DIF_PREV_YEAR_PERC_BOTTOM": -0.1593,
    "Y2D_RANK_DIF_PREV_YEAR_BOTTOM": 2,
    "Y2D_APT_NAME_BOTTOM": "Bristol",
    "Y2D_TO_DATE_BOTTOM": "2024-10-28",
    "Y2D_APT_ARR_PUNCT_BOTTOM": 0.6397,
    "Y2D_PUNCT_DIF_PREV_YEAR_PERC_BOTTOM": 0.0507,
    "Y2D_PUNCT_DIF_2019_PERC_BOTTOM": -0.0766
  },
  {
    "RANK": 10,
    "DY_RANK_DIF_PREV_WEEK": -2,
    "DY_APT_NAME": "Stockholm Arlanda",
    "DY_TO_DATE": "2024-10-28",
    "DY_APT_ARR_PUNCT": 0.881,
    "DY_PUNCT_DIF_PREV_WEEK_PERC": 0.0325,
    "DY_PUNCT_DIF_PREV_YEAR_PERC": 0.1077,
    "WK_RANK_DIF_PREV_WEEK": 4,
    "WK_APT_NAME": "Podgorica",
    "WK_FROM_DATE": "2024-10-22",
    "WK_TO_DATE": "2024-10-28",
    "WK_APT_ARR_PUNCT": 0.8319,
    "WK_PUNCT_DIF_PREV_WEEK_PERC": 0.0287,
    "WK_PUNCT_DIF_PREV_YEAR_PERC": 0.0726,
    "Y2D_RANK_DIF_PREV_YEAR": 62,
    "Y2D_APT_NAME": "Copenhagen",
    "Y2D_TO_DATE": "2024-10-28",
    "Y2D_APT_ARR_PUNCT": 0.783,
    "Y2D_PUNCT_DIF_PREV_YEAR_PERC": 0.0972,
    "Y2D_PUNCT_DIF_2019_PERC": -0.0238,
    "DY_RANK_DIF_PREV_WEEK_BOTTOM": -70,
    "DY_APT_NAME_BOTTOM": "Paris Charles de Gaulle",
    "DY_TO_DATE_BOTTOM": "2024-10-28",
    "DY_APT_ARR_PUNCT_BOTTOM": 0.6012,
    "DY_PUNCT_DIF_PREV_WEEK_PERC_BOTTOM": -0.2048,
    "DY_PUNCT_DIF_PREV_YEAR_PERC_BOTTOM": -0.1806,
    "WK_RANK_DIF_PREV_WEEK_BOTTOM": -72,
    "WK_APT_NAME_BOTTOM": "Palma de Mallorca",
    "WK_FROM_DATE_BOTTOM": "2024-10-22",
    "WK_TO_DATE_BOTTOM": "2024-10-28",
    "WK_APT_ARR_PUNCT_BOTTOM": 0.6445,
    "WK_PUNCT_DIF_PREV_WEEK_PERC_BOTTOM": -0.1244,
    "WK_PUNCT_DIF_PREV_YEAR_PERC_BOTTOM": -0.1271,
    "Y2D_RANK_DIF_PREV_YEAR_BOTTOM": -12,
    "Y2D_APT_NAME_BOTTOM": "Tirana",
    "Y2D_TO_DATE_BOTTOM": "2024-10-28",
    "Y2D_APT_ARR_PUNCT_BOTTOM": 0.6449,
    "Y2D_PUNCT_DIF_PREV_YEAR_PERC_BOTTOM": -0.0172,
    "Y2D_PUNCT_DIF_2019_PERC_BOTTOM": -0.0054
  }
]
